metrify/__init__.py
metrify/metrics.py
metrify-0.1.3.2.dist-info/METADATA
metrify-0.1.3.2.dist-info/WHEEL
metrify-0.1.3.2.dist-info/licenses/LICENSE
metrify-0.1.3.2.dist-info/RECORD
