Metadata-Version: 2.3
Name: metrify
Version: 0.1.3.2
Summary: A package for computing informedness, markedness and phi score
Project-URL: Homepage, https://github.com/giacomopiccinini/metrify
Author-email: Giacomo Piccinini <giacomo.piccinini@proton.me>
License-File: LICENSE
Classifier: License :: OSI Approved :: MIT License
Classifier: Operating System :: OS Independent
Classifier: Programming Language :: Python :: 3
Requires-Python: >=3.7
Requires-Dist: numpy
Requires-Dist: scikit-learn
